orcan/__init__.py
orcan/orcan.py
orcan/core/__init__.py
orcan/core/config.py
orcan/core/runner.py
orcan/modules/__init__.py
orcan/modules/domain.py
orcan/modules/who.py
orcan-0.0.2.dist-info/LICENSE
orcan-0.0.2.dist-info/METADATA
orcan-0.0.2.dist-info/WHEEL
orcan-0.0.2.dist-info/entry_points.txt
orcan-0.0.2.dist-info/top_level.txt
orcan-0.0.2.dist-info/RECORD
