Metadata-Version: 2.1
Name: orcan
Version: 0.0.2
Summary: not the best reconnaissance tool, but it is a reconnaissance tool
Home-page: https://erfansamandarian.com/soundbook
Author: Erfan Samandarian
Author-email: mail@erfansamandarian.com
License: MIT
License-File: LICENSE
Requires-Dist: requests
Requires-Dist: tabulate
Requires-Dist: termcolor
